firebase_messaging/__init__.py
firebase_messaging/const.py
firebase_messaging/fcmpushclient.py
firebase_messaging/fcmregister.py
firebase_messaging/py.typed
firebase_messaging/proto/android_checkin.proto
firebase_messaging/proto/android_checkin_pb2.py
firebase_messaging/proto/android_checkin_pb2.pyi
firebase_messaging/proto/checkin.proto
firebase_messaging/proto/checkin_pb2.py
firebase_messaging/proto/checkin_pb2.pyi
firebase_messaging/proto/mcs.proto
firebase_messaging/proto/mcs_pb2.py
firebase_messaging/proto/mcs_pb2.pyi
firebase_messaging-0.4.4.dist-info/METADATA
firebase_messaging-0.4.4.dist-info/WHEEL
firebase_messaging-0.4.4.dist-info/licenses/LICENSE
firebase_messaging-0.4.4.dist-info/RECORD
