Metadata-Version: 2.3
Name: firebase-messaging
Version: 0.4.4
Summary: FCM/GCM push notification client
Project-URL: Homepage, https://github.com/sdb9696/firebase-messaging
Project-URL: Repository, https://github.com/sdb9696/firebase-messaging
Project-URL: Documentation, http://firebase-messaging.readthedocs.io/
Project-URL: Bug Tracker, https://github.com/sdb9696/firebase-messaging/issues
Author-email: sdb9696 <sdb9696@users.noreply.github.com>
License: MIT
License-File: LICENSE
Keywords: Firebase,Firebase Cloud Messaging,Google Cloud Messaging
Classifier: Environment :: Other Environment
Classifier: Intended Audience :: Developers
Classifier: License :: OSI Approved :: MIT License
Classifier: Operating System :: OS Independent
Classifier: Programming Language :: Python :: 3
Classifier: Programming Language :: Python :: 3.9
Classifier: Programming Language :: Python :: 3.10
Classifier: Programming Language :: Python :: 3.11
Classifier: Programming Language :: Python :: 3.12
Classifier: Programming Language :: Python :: 3.13
Classifier: Topic :: Software Development :: Libraries :: Python Modules
Requires-Python: >=3.9.0
Requires-Dist: aiohttp>=3.9.3
Requires-Dist: cryptography>=2.5
Requires-Dist: http-ece~=1.1.0
Requires-Dist: protobuf<6,>=4.24.3
Provides-Extra: docs
Requires-Dist: myst-parser; extra == 'docs'
Requires-Dist: sphinx-autodoc-typehints~=1.24; extra == 'docs'
Requires-Dist: sphinx-rtd-theme~=1.3; extra == 'docs'
Requires-Dist: sphinx==7.1.2; extra == 'docs'
